<?xml version="1.0" encoding="utf-8"?>
<odoo>

    <record id="res_config_settings_view_form" model="ir.ui.view">
        <field name="model">res.config.settings</field>
        <field name="inherit_id" ref="base_setup.res_config_settings_view_form"/>
        <field name="arch" type="xml">
            <xpath expr="//field[@name='cal_client_id']" position="replace">
                <field name="dummy_cal_client_id" nolabel="1"/>
            </xpath>
            <xpath expr="//label[@for='cal_client_id']" position="replace">
                <label for="dummy_cal_client_id" string="Client ID" class="col-3 col-lg-3 o_light_label"/>
            </xpath>
            <xpath expr="//field[@name='cal_client_secret']" position="replace">
                <field name="dummy_cal_client_secret" nolabel="1"/>
            </xpath>
            <xpath expr="//label[@for='cal_client_secret']" position="replace">
                <label for="dummy_cal_client_secret" string="Client Secret" class="col-3 col-lg-3 o_light_label"/>
            </xpath>
        </field>
    </record>

</odoo>

